<?xml version="1.0"?>

<Form Name="frmTextEntry_Keyboard" Width="240" Height="320" Caption="Enter Number">
  <Edit Name="prpText"  Caption="Number: "   X="2" Y="20" Width="200" Height="22" CaptionWidth="70" ReadOnly="1" />

  <Button   Caption="9"    X="40" Y="65" Width="40"  Height="40" OnClick="OnKey"/>
  <Button   Caption="8"    X="80" Y="65" Width="40"  Height="40" OnClick="OnKey"/>
  <Button   Caption="7"    X="120" Y="65" Width="40"  Height="40" OnClick="OnKey"/>

  <Button   Caption="4"    X="40" Y="105" Width="40"  Height="40" OnClick="OnKey"/>
  <Button   Caption="5"    X="80" Y="105" Width="40"  Height="40" OnClick="OnKey"/>
  <Button   Caption="6"    X="120" Y="105" Width="40"  Height="40" OnClick="OnKey"/>

  <Button   Caption="1"    X="40" Y="145" Width="40"  Height="40" OnClick="OnKey"/>
  <Button   Caption="2"    X="80" Y="145" Width="40"  Height="40" OnClick="OnKey"/>
  <Button   Caption="3"    X="120" Y="145" Width="40"  Height="40" OnClick="OnKey"/>

  <Button   Caption="0"    X="40" Y="185" Width="120"  Height="40" OnClick="OnKey"/>

  <Button Caption="Clear" X="40" Y="230" Width="60"  Height="40" OnClick="OnClear"/>
  <Button   Caption="Ok"   X="100" Y="230" Width="60"  Height="40" OnClick="OnOk"/>
</Form>
